{
    "took": 0,
    "timed_out": false,
    "_shards": {
      "total": 5,
      "successful": 5,
      "skipped": 0,
      "failed": 0
    },
    "hits": {
      "total": 5,
      "max_score": 1,
      "hits": [
        {
          "_index": "escuela",
          "_type": "curso",
          "_id": "5",
          "_score": 1,
          "_source": {
            "id": "5",
            "curso": "EB",
            "nombre": "Estadistica basica"
          }
        },
        {
          "_index": "escuela",
          "_type": "curso",
          "_id": "2",
          "_score": 1,
          "_source": {
            "id": "2",
            "curso": "PB",
            "nombre": "Programacion Basica"
          }
        },
        {
          "_index": "escuela",
          "_type": "curso",
          "_id": "4",
          "_score": 1,
          "_source": {
            "id": "4",
            "curso": "EDA",
            "nombre": "Estadistica aplicada"
          }
        },
        {
          "_index": "escuela",
          "_type": "curso",
          "_id": "1",
          "_score": 1,
          "_source": {
            "id": "1",
            "curso": "FL",
            "nombre": "Filosofia"
          }
        },
        {
          "_index": "escuela",
          "_type": "curso",
          "_id": "3",
          "_score": 1,
          "_source": {
            "id": "3",
            "curso": "PAV",
            "nombre": "Programacion avanzada"
          }
        }
      ]
    }
  }